PyNAFF/PyNAFF.py
PyNAFF/__init__.py
pynaff-1.1.7.dist-info/licenses/LICENSE.txt
pynaff-1.1.7.dist-info/METADATA
pynaff-1.1.7.dist-info/WHEEL
pynaff-1.1.7.dist-info/top_level.txt
pynaff-1.1.7.dist-info/RECORD
