Metadata-Version: 2.4
Name: PyNAFF
Version: 1.1.7
Summary: A Python module that implements the Numerical Analysis of Fundamental Frequencies (NAFF) algorithm
Home-page: https://github.com/nkarast/PyNAFF
Author: Nikos Karastathis
Author-email: nkarast@gmail.com
License: GPLv3
Keywords: NAFF,FREQUENCY ANALYSIS
Classifier: Development Status :: 5 - Production/Stable
Classifier: Intended Audience :: Developers
Classifier: Topic :: Software Development :: Build Tools
Classifier: License :: OSI Approved :: GNU General Public License v3 (GPLv3)
Classifier: Programming Language :: Python :: 3
Classifier: Programming Language :: Python :: 3.9
License-File: LICENSE.txt
Requires-Dist: numpy
Dynamic: author
Dynamic: author-email
Dynamic: classifier
Dynamic: home-page
Dynamic: keywords
Dynamic: license
Dynamic: license-file
Dynamic: requires-dist
Dynamic: summary
